[
   {
      "name": "Niclas Hedhman",
      "imports": [
         "Peter Firmstone",
         "Peter Firmstone",
         "Peter Firmstone",
         "Gregg Wonderly",
         "Peter Firmstone"
      ]
   },
   {
      "name": "Mark Brouwer (JIRA)",
      "imports": []
   },
   {
      "name": "Sim IJskes - QCG",
      "imports": [
         "Peter Firmstone"
      ]
   },
   {
      "name": "Sam Chance",
      "imports": [
         "Peter Firmstone",
         "Dennis Reedy",
         "Mike McGrady",
         "Peter Firmstone"
      ]
   },
   {
      "name": "Brian Murphy (JIRA)",
      "imports": [
         "Mark Brouwer (JIRA)",
         "Mark Brouwer (JIRA)",
         "Mark Brouwer (JIRA)"
      ]
   },
   {
      "name": "Mike McGrady",
      "imports": [
         "Peter Firmstone",
         "Peter Firmstone",
         "Peter Firmstone",
         "Dennis Reedy",
         "Peter Firmstone",
         "Sam Chance",
         "Dennis Reedy",
         "Peter Firmstone",
         "Peter Firmstone",
         "Dennis Reedy",
         "Dennis Reedy"
      ]
   },
   {
      "name": "Peter Firmstone (JIRA)",
      "imports": []
   },
   {
      "name": "Calum Shaw-Mackay",
      "imports": [
         "Peter Firmstone",
         "Peter Firmstone"
      ]
   },
   {
      "name": "Jim Hurley (JIRA)",
      "imports": []
   },
   {
      "name": "richard nicholson",
      "imports": [
         "Niclas Hedhman"
      ]
   },
   {
      "name": "Gregg Wonderly",
      "imports": [
         "Peter Firmstone",
         "Peter Firmstone",
         "Niclas Hedhman",
         "Niclas Hedhman",
         "Calum Shaw-Mackay",
         "Peter Firmstone",
         "Peter Firmstone",
         "Mike McGrady"
      ]
   },
   {
      "name": "Jonathan Costers (JIRA)",
      "imports": [
         "Peter Firmstone (JIRA)",
         "Peter Firmstone (JIRA)",
         "Peter Firmstone (JIRA)",
         "Peter Firmstone (JIRA)"
      ]
   },
   {
      "name": "Dennis Reedy",
      "imports": [
         "Peter Firmstone",
         "Peter Firmstone",
         "Mike McGrady"
      ]
   },
   {
      "name": "Jonathan Costers",
      "imports": [
         "Peter Firmstone",
         "Peter Firmstone"
      ]
   },
   {
      "name": "Peter Firmstone",
      "imports": [
         "Gregg Wonderly",
         "Gregg Wonderly",
         "Gregg Wonderly",
         "Gregg Wonderly",
         "Mike McGrady",
         "Mike McGrady",
         "Sam Chance",
         "Mike McGrady",
         "Dennis Reedy",
         "Sam Chance",
         "Niclas Hedhman",
         "Gregg Wonderly",
         "Calum Shaw-Mackay",
         "Gregg Wonderly",
         "Niclas Hedhman",
         "Niclas Hedhman",
         "Gregg Wonderly",
         "Jonathan Costers",
         "Jonathan Costers",
         "Niclas Hedhman",
         "Niclas Hedhman",
         "Jonathan Costers",
         "Calum Shaw-Mackay",
         "Gregg Wonderly",
         "Jonathan Costers (JIRA)",
         "Gregg Wonderly",
         "Dennis Reedy",
         "Brian Murphy (JIRA)",
         "Mike McGrady",
         "Sim IJskes - QCG",
         "Sim IJskes - QCG",
         "Mike McGrady",
         "Gregg Wonderly",
         "Jonathan Costers",
         "Peter Firmstone (JIRA)"
      ]
   },
   {
      "name": "Sim IJskes (JIRA)",
      "imports": [
         "Jim Hurley (JIRA)"
      ]
   }
]