[
   {
      "imports": [
         "Anne Yu",
         "shen guoquan",
         "shen guoquan",
         "shen guoquan"
      ],
      "name": "Li Li"
   },
   {
      "imports": [
         "Joe Brockmeier",
         "Ryan Pridgeon",
         "Prasad Mujumdar",
         "Patrick Hunt",
         "Joe Brockmeier",
         "Patrick Hunt",
         "Anne Yu",
         "Lenni Kuff",
         "Lenni Kuff",
         "Ma, Junjie",
         "Anne Yu",
         "Anne Yu",
         "Prasad Mujumdar",
         "Li Li",
         "shen guoquan"
      ],
      "name": "Sravya Tirukkovalur"
   },
   {
      "imports": [
         "Lenni Kuff",
         "Sravya Tirukkovalur",
         "Lenni Kuff",
         "Colin Ma",
         "Sravya Tirukkovalur",
         "Colin Ma",
         "Sravya Tirukkovalur",
         "Ma, Junjie",
         "Lenni Kuff",
         "Sun, Dapeng",
         "Li Li"
      ],
      "name": "Anne Yu"
   },
   {
      "imports": [
         "Sravya Tirukkovalur",
         "Sravya Tirukkovalur"
      ],
      "name": "Joe Brockmeier"
   },
   {
      "imports": [
         "Ma, Junjie"
      ],
      "name": "Gregory Chanan"
   },
   {
      "imports": [
         "Anne Yu",
         "Dapeng Sun",
         "Dapeng Sun",
         "shen guoquan",
         "Anne Yu",
         "shen guoquan"
      ],
      "name": "Colin Ma"
   },
   {
      "imports": [
         "Anne Yu"
      ],
      "name": "Shen, Guoquan"
   },
   {
      "imports": [
         "Colin Ma",
         "Colin Ma",
         "Colin Ma"
      ],
      "name": "Dapeng Sun"
   },
   {
      "imports": [
         "Prasad Mujumdar",
         "Sravya Tirukkovalur"
      ],
      "name": "Patrick Hunt"
   },
   {
      "imports": [
         "Colin Ma",
         "Sravya Tirukkovalur",
         "Colin Ma",
         "Li Li",
         "Li Li",
         "Li Li",
         "Li Li",
         "Li Li"
      ],
      "name": "shen guoquan"
   },
   {
      "imports": [
         "Lenni Kuff",
         "Lenni Kuff",
         "Sravya Tirukkovalur"
      ],
      "name": "Ryan Pridgeon"
   },
   {
      "imports": [
         "Sravya Tirukkovalur",
         "Anne Yu",
         "Anne Yu",
         "Lenni Kuff",
         "Lenni Kuff"
      ],
      "name": "Sun, Dapeng"
   },
   {
      "imports": [
         "Sravya Tirukkovalur",
         "Sravya Tirukkovalur"
      ],
      "name": "Prasad Mujumdar"
   },
   {
      "imports": [
         "Sravya Tirukkovalur",
         "Gregory Chanan",
         "Sun, Dapeng",
         "Lenni Kuff"
      ],
      "name": "Ma, Junjie"
   },
   {
      "imports": [
         "Sravya Tirukkovalur",
         "Ryan Pridgeon",
         "Anne Yu",
         "Anne Yu",
         "Ryan Pridgeon",
         "Ryan Pridgeon",
         "Anne Yu",
         "Anne Yu",
         "Sravya Tirukkovalur",
         "Sun, Dapeng",
         "Anne Yu",
         "Sun, Dapeng",
         "Sravya Tirukkovalur",
         "Sravya Tirukkovalur"
      ],
      "name": "Lenni Kuff"
   },
   {
      "imports": [
         "Gregory Chanan"
      ],
      "name": "Vamsee Yarlagadda"
   }
]