[
   {
      "name": "Nathan Marz",
      "imports": [
         "Ted Dunning"
      ]
   },
   {
      "name": "hilfi alkaff",
      "imports": [
         "Ruihao Ye"
      ]
   },
   {
      "name": "=?UTF-8?B?SGVyYmVydCBNw7xobGJ1cmdlcg==?=",
      "imports": [
         "Hugh Xedni"
      ]
   },
   {
      "name": "James Xu",
      "imports": [
         "Ted Dunning",
         "amit bohra",
         "hilfi alkaff"
      ]
   },
   {
      "name": "Bobby Evans",
      "imports": [
         "Josh Walton",
         "=?UTF-8?B?SGVyYmVydCBNw7xobGJ1cmdlcg==?=",
         "Ted Dunning"
      ]
   },
   {
      "name": "=?GB2312?B?wO680rrq?=",
      "imports": [
         "Ruihao Ye"
      ]
   },
   {
      "name": "Ted Dunning",
      "imports": [
         "Ashish",
         "Brian O''Neill",
         "Doug Cutting",
         "Bobby Evans",
         "Gianmarco De Francisci Morales"
      ]
   },
   {
      "name": "Gianmarco De Francisci Morales",
      "imports": [
         "Matt Franklin"
      ]
   },
   {
      "name": "Josh Walton",
      "imports": [
         "Bobby Evans"
      ]
   },
   {
      "name": "=?UTF-8?B?6IKW5bq3KEthbmcgWGlhbyk=?=",
      "imports": [
         "Alexander Yerenkow (JIRA)"
      ]
   },
   {
      "name": "FangKun Cao",
      "imports": [
         "Doug Cutting",
         "padma priya chitturi",
         "padma priya chitturi",
         "padma priya chitturi"
      ]
   },
   {
      "name": "Ashish",
      "imports": [
         "P. Taylor Goetz"
      ]
   },
   {
      "name": "padma priya chitturi",
      "imports": [
         "FangKun Cao"
      ]
   },
   {
      "name": "Doug Cutting",
      "imports": [
         "P. Taylor Goetz",
         "P. Taylor Goetz",
         "P. Taylor Goetz",
         "P. Taylor Goetz",
         "P. Taylor Goetz",
         "P. Taylor Goetz"
      ]
   },
   {
      "name": "amit bohra",
      "imports": []
   },
   {
      "name": "Ed Kohlwey",
      "imports": [
         "Ted Dunning"
      ]
   },
   {
      "name": "Alexander Yerenkow (JIRA)",
      "imports": []
   },
   {
      "name": "Adrian Petrescu",
      "imports": [
         "Adrian Petrescu (JIRA)"
      ]
   },
   {
      "name": "Derek Dagit",
      "imports": [
         "P. Taylor Goetz"
      ]
   },
   {
      "name": "Adrian Petrescu (JIRA)",
      "imports": []
   },
   {
      "name": "P. Taylor Goetz",
      "imports": [
         "Doug Cutting",
         "Ashish",
         "Doug Cutting",
         "Derek Dagit",
         "Nathan Marz",
         "Bobby Evans",
         "Bobby Evans",
         "Matt Franklin",
         "Matt Franklin",
         "Matt Franklin",
         "Doug Cutting",
         "Doug Cutting",
         "Matt Franklin",
         "Doug Cutting"
      ]
   },
   {
      "name": "Matt Franklin",
      "imports": [
         "Ted Dunning",
         "James Xu",
         "P. Taylor Goetz",
         "P. Taylor Goetz"
      ]
   },
   {
      "name": "Brian O''Neill",
      "imports": []
   },
   {
      "name": "Supun Kamburugamuva",
      "imports": [
         "Ed Kohlwey"
      ]
   },
   {
      "name": "Ruihao Ye",
      "imports": [
         "hilfi alkaff"
      ]
   },
   {
      "name": "Hugh Xedni",
      "imports": [
         "Supun Kamburugamuva"
      ]
   }
]