[
    {
        "name": "Peter Darton",
        "imports": []
    },
    {
        "name": "Nicolas Belisle",
        "imports": []
    },
    {
        "name": "Stefano Mazzocchi",
        "imports": [
            "David Nuescheler",
            "David Nuescheler",
            "Jukka Zitting"
        ]
    },
    {
        "name": "Peeter Piegaze",
        "imports": [
            "Ashley Martens",
            "Michael Daglian"
        ]
    },
    {
        "name": "Martin Van Den Bemt",
        "imports": [
            "Stefan Guggisberg",
            "Roy T. Fielding",
            "Michael Wilson",
            "Stefan"
        ]
    },
    {
        "name": "Marcel Reutegger",
        "imports": [
            "Martin Perez",
            "Martin Perez",
            "Brian Moseley",
            "Benois",
            "Stefan Guggisberg",
            "Martin Perez",
            "Pankaj Gupta",
            "Martin Perez",
            "Brian Moseley",
            "Brian Moseley",
            "Brian Moseley",
            "Brian Moseley",
            "Brian Moseley",
            "Brian Moseley",
            "Benois",
            "Brian Moseley",
            "Cyrus Daboo",
            "Ashley Martens"
        ]
    },
    {
        "name": "Angela Schreiber",
        "imports": [
            "Brian Moseley"
        ]
    },
    {
        "name": "David Nuescheler",
        "imports": [
            "Stefano Mazzocchi",
            "Felix Meschberger",
            "Jukka Zitting",
            "Sylvain Wallez"
        ]
    },
    {
        "name": "Michael Daglian",
        "imports": [
            "Tobias Bocanegra",
            "Peeter Piegaze"
        ]
    },
    {
        "name": "Marek Blotny",
        "imports": []
    },
    {
        "name": "Costin Leau",
        "imports": [
            "Kevin Wiggen"
        ]
    },
    {
        "name": "Sandro.boehme",
        "imports": [
            "Martin Perez"
        ]
    },
    {
        "name": "Benois",
        "imports": [
            "Jukka Zitting",
            "Marcel Reutegger",
            "Stefan Guggisberg"
        ]
    },
    {
        "name": "Roy T. Fielding",
        "imports": [
            "Martin Van Den Bemt",
            "Stefano Mazzocchi",
            "Jukka Zitting",
            "Jukka Zitting"
        ]
    },
    {
        "name": "Kevin Wiggen",
        "imports": []
    },
    {
        "name": "Celina Konito",
        "imports": []
    },
    {
        "name": "Paul Skinner",
        "imports": []
    },
    {
        "name": "Jukka Zitting",
        "imports": [
            "Felix Meschberger",
            "Felix Meschberger",
            "Tobias Bocanegra",
            "Tobias Bocanegra",
            "Kennedy, Colleen",
            "Sirne Vip",
            "Sirne Vip",
            "Felix Meschberger",
            "Felix Meschberger",
            "Celina Konito",
            "Celina Konito",
            "Sirne Vip",
            "Leila Rizkallah",
            "Leila Rizkallah",
            "Celina Konito",
            "Celina Konito",
            "Kennedy, Colleen",
            "Nicolas Belisle",
            "Tobias Strasser",
            "Martin Perez",
            "Tobias Strasser",
            "Joseph Chen",
            "Brian Moseley",
            "Brian Moseley",
            "Stefan Guggisberg",
            "Brian Moseley",
            "Roy T. Fielding",
            "Sirne Vip",
            "Roy T. Fielding",
            "Brian Moseley",
            "Costin Leau",
            "Costin Leau",
            "Costin Leau",
            "Costin Leau"
        ]
    },
    {
        "name": "Tobias Bocanegra",
        "imports": [
            "Peeter Piegaze",
            "Jukka Zitting",
            "Marek Blotny",
            "Jukka Zitting",
            "Brian Moseley",
            "Guenther.humer",
            "Costin Leau",
            "Costin Leau"
        ]
    },
    {
        "name": "Stefan",
        "imports": []
    },
    {
        "name": "Stefan Guggisberg",
        "imports": [
            "Benois",
            "Brian Moseley",
            "Brian Moseley",
            "Brian Moseley",
            "Fabio Boulos",
            "Martin Van Den Bemt",
            "Paul Skinner",
            "Jukka Zitting",
            "Brian Moseley",
            "Brian Moseley",
            "Laurent Belmonte",
            "Benois",
            "Brian Moseley",
            "Brian Moseley",
            "Brian Moseley",
            "Costin Leau",
            "Brian Moseley"
        ]
    },
    {
        "name": "Joseph Chen",
        "imports": []
    },
    {
        "name": "Felix Meschberger",
        "imports": [
            "Jukka Zitting",
            "Jukka Zitting",
            "Jukka Zitting",
            "Stefano Mazzocchi"
        ]
    },
    {
        "name": "Kennedy, Colleen",
        "imports": []
    },
    {
        "name": "Edgar Poce",
        "imports": [
            "Martin Perez",
            "Martin Perez",
            "Jukka Zitting",
            "Brian Moseley"
        ]
    },
    {
        "name": "Guenther.humer",
        "imports": []
    },
    {
        "name": "Przemyslaw Pakulski",
        "imports": []
    },
    {
        "name": "Daniel Florey",
        "imports": []
    },
    {
        "name": "Nicolas Jouanin",
        "imports": [
            "Stefan Guggisberg"
        ]
    },
    {
        "name": "Fabio Boulos",
        "imports": [
            "Stefan Guggisberg"
        ]
    },
    {
        "name": "Giacomo Pati",
        "imports": [
            "Felix Meschberger"
        ]
    },
    {
        "name": "Brian Moseley",
        "imports": [
            "Jukka Zitting",
            "Marcel Reutegger",
            "Stefan Guggisberg",
            "Stefan Guggisberg",
            "Stefan Guggisberg",
            "Marcel Reutegger",
            "Edgar Poce",
            "Stefan Guggisberg",
            "Stefano Mazzocchi",
            "Daniel Florey",
            "Stefan Guggisberg",
            "Stefan Guggisberg",
            "Angela Schreiber",
            "Marcel Reutegger",
            "Marcel Reutegger",
            "Stefan Guggisberg",
            "Marcel Reutegger",
            "Tobias Bocanegra",
            "Marcel Reutegger",
            "Jukka Zitting",
            "Stefan Guggisberg",
            "Marcel Reutegger",
            "Stefan Guggisberg",
            "Marcel Reutegger",
            "Gregory Block",
            "Stefan Guggisberg",
            "Alexandru Popescu",
            "Stefan Guggisberg",
            "Stefan Guggisberg"
        ]
    },
    {
        "name": "Serge Huber",
        "imports": [
            "Roy Russo",
            "Stefan Guggisberg"
        ]
    },
    {
        "name": "Sirne Vip",
        "imports": [
            "Jukka Zitting",
            "Jukka Zitting"
        ]
    },
    {
        "name": "Tobias Strasser",
        "imports": []
    },
    {
        "name": "Patrick Kimber",
        "imports": [
            "Martin Perez"
        ]
    },
    {
        "name": "Laurent Belmonte",
        "imports": [
            "Martin Perez",
            "Stefan Guggisberg"
        ]
    },
    {
        "name": "Michael Wilson",
        "imports": []
    },
    {
        "name": "Michael Wechner",
        "imports": [
            "David Nuescheler"
        ]
    },
    {
        "name": "Angela",
        "imports": [
            "Peter Darton"
        ]
    },
    {
        "name": "Gregory Block",
        "imports": [
            "Cyrus Daboo",
            "Stefano Mazzocchi",
            "Brian Moseley"
        ]
    },
    {
        "name": "Scroisier2",
        "imports": [
            "Stefano Mazzocchi"
        ]
    },
    {
        "name": "Leila Rizkallah",
        "imports": []
    },
    {
        "name": "Roy Russo",
        "imports": []
    },
    {
        "name": "Alexandru Popescu",
        "imports": [
            "Marcel Reutegger",
            "Scharles",
            "Brian Moseley",
            "Brian Moseley"
        ]
    },
    {
        "name": "Solprovider",
        "imports": [
            "Leila Rizkallah"
        ]
    },
    {
        "name": "Ashley Martens",
        "imports": []
    },
    {
        "name": "Pankaj Gupta",
        "imports": []
    },
    {
        "name": "Dominique Pfister",
        "imports": [
            "Kevin Wiggen",
            "Przemyslaw Pakulski"
        ]
    },
    {
        "name": "Sylvain Wallez",
        "imports": [
            "David Nuescheler",
            "David Nuescheler"
        ]
    },
    {
        "name": "Scharles",
        "imports": []
    },
    {
        "name": "Martin Perez",
        "imports": [
            "Roy Russo",
            "Laurent Belmonte",
            "Brian Moseley",
            "Marcel Reutegger",
            "Marcel Reutegger",
            "Marcel Reutegger",
            "Patrick Kimber"
        ]
    },
    {
        "name": "Cyrus Daboo",
        "imports": [
            "Marcel Reutegger"
        ]
    }
]