[{"name": "Roy T. Fielding", "imports": ["Nhedhman"]}, {"name": "Mzaun", "imports": ["Mcaisse"]}, {"name": "Mbouschen", "imports": ["Crussell", "Crussell", "Crussell", "Ajefferson", "Ajefferson", "Crussell", "Ajefferson", "Crussell"]}, {"name": "Ghendrey", "imports": ["Mcaisse"]}, {"name": "Mwatzek", "imports": ["Clr", "Ajefferson", "Mcaisse", "Crussell", "Mcaisse", "Ajefferson", "Ajefferson", "Ajefferson", "Ajefferson", "Ajefferson", "Mcaisse"]}, {"name": "Crussell", "imports": ["Mbouschen", "Mbouschen", "Mcaisse", "Mcaisse", "Ajefferson", "Mcaisse", "Ajefferson", "Mcaisse", "Mwatzek", "Mwatzek", "Ajefferson", "Mbouschen", "Mwatzek", "Mbouschen", "Mbouschen", "Mbouschen", "Mwatzek", "Ajefferson", "Mwatzek", "Ajefferson", "Ajefferson", "Ajefferson", "Erik", "Ajefferson"]}, {"name": "Mcaisse", "imports": ["Crussell", "Mwatzek", "Ajefferson", "Ajefferson", "Mwatzek", "Mwatzek", "Ajefferson", "Crussell", "Ajefferson", "Mwatzek", "Crussell", "Crussell"]}, {"name": "Nhedhman", "imports": []}, {"name": "Erik", "imports": ["Ajefferson"]}, {"name": "Clr", "imports": []}, {"name": "Ajefferson", "imports": ["Mwatzek", "Mwatzek", "Mwatzek", "Mcaisse", "Crussell", "Mcaisse", "Crussell", "Mwatzek", "Mbouschen", "Mbouschen", "Mwatzek", "Mwatzek", "Mwatzek", "Mwatzek", "Mwatzek", "Crussell", "Crussell"]}]