[{"imports": ["Thoward*"], "name": "Andrey"}, {"imports": ["Pnasser*", "Sbodewig", "Sbodewig", "Thoward*", "Pnasser*", "Sbodewig", "Pnasser*", "Bkr", "Pnasser*", "Thoward*", "Wbarnett", "Thoward*", "Sbodewig", "Thoward*", "Sbodewig"], "name": "Mherndon"}, {"imports": [], "name": "Jtaal"}, {"imports": [], "name": "Vanna"}, {"imports": ["Thoward*"], "name": "Granroth, Neal V."}, {"imports": ["Ccurrens", "Ccurrens", "Pmateja"], "name": "Wgao"}, {"imports": ["Thoward*"], "name": "Gdarkin"}, {"imports": ["Pnasser*", "Thoward*"], "name": "Bfoster"}, {"imports": ["Sbodewig", "Apowell", "Apowell", "Lscott", "Wbarnett", "Llucene", "Ddigy"], "name": "Smirvoda"}, {"imports": ["Sbodewig", "Rjordan", "Sbodewig", "Sbodewig", "Wgao"], "name": "Arahien"}, {"imports": ["Pbizhan", "Rpanwar", "Pbizhan", "Jtaal", "Jtaal", "Thoward*", "Thoward*", "Thoward*", "Sbodewig"], "name": "Slombard*"}, {"imports": ["Apook", "Apook", "Rpanwar", "Jtaal", "Vladimir", "Vladimir", "Vanna", "Thoward*", "Thoward*"], "name": "Digy"}, {"imports": [], "name": "Sbodewig"}, {"imports": ["Wgao", "Thoward*", "Smirvoda", "Mherndon", "Pnasser*", "Mherndon"], "name": "Wbarnett"}, {"imports": ["Thoward*", "Thoward*"], "name": "Lscott"}, {"imports": ["Pbizhan"], "name": "Apook"}, {"imports": ["Wgao", "Wgao", "Wgao"], "name": "Ccurrens"}, {"imports": ["Sbodewig", "Bfoster", "Sbodewig", "Sbodewig", "Mherndon", "Sbodewig", "Thoward*", "Thoward*", "Thoward*", "Thoward*", "Thoward*", "Thoward*", "Thoward*", "Thoward*", "Smirvoda", "Mherndon", "Thoward*", "Thoward*", "Thoward*"], "name": "Pnasser*"}, {"imports": ["Smirvoda"], "name": "Blat001"}, {"imports": ["Bfoster", "Pnasser*", "Sbodewig", "Pnasser*", "Apowell", "Smirvoda", "Arahien", "Sbodewig", "Smirvoda", "Pnasser*", "Pnasser*", "Pnasser*", "Sbodewig", "Pbizhan", "Slombard*", "Slombard*", "Slombard*", "Sbodewig", "Sbodewig", "Mherndon", "Lscott", "Sbodewig", "Mherndon", "Sbodewig", "Granroth, Neal V.", "Sbodewig", "Wbarnett", "Mherndon", "Sbodewig", "Mherndon", "Bkr", "Pnasser*", "Slombard*", "Sbodewig", "Pnasser*"], "name": "Thoward*"}, {"imports": ["Thoward*", "Gdarkin", "Thoward*"], "name": "Ddigy"}, {"imports": ["Mherndon"], "name": "Bkr"}, {"imports": ["Pnasser*", "Apowell", "Apowell"], "name": "Llucene"}, {"imports": ["Mscheffer"], "name": "Schiaretta"}, {"imports": [], "name": "Pbizhan"}, {"imports": ["Wgao"], "name": "Pmateja"}, {"imports": ["Sbodewig", "Sbodewig", "Thoward*"], "name": "Rjordan"}, {"imports": ["Schiaretta"], "name": "Mscheffer"}, {"imports": [], "name": "Rpanwar"}, {"imports": ["Pnasser*"], "name": "Nwise"}, {"imports": [], "name": "Vladimir"}, {"imports": ["Smirvoda", "Thoward*", "Sbodewig", "Sbodewig", "Llucene"], "name": "Apowell"}, {"imports": ["Pnasser*"], "name": "Hmerkl"}]