[
    {
        "imports": [],
        "name": "Eric Jensen"
    },
    {
        "imports": [
            "Jeff Brown"
        ],
        "name": "Mathias Herberts"
    },
    {
        "imports": [
            "Nicholas Telford"
        ],
        "name": "Chris Goffinet"
    },
    {
        "imports": [],
        "name": "Nathan Marz"
    },
    {
        "imports": [],
        "name": "Jonathan Ellis"
    },
    {
        "imports": [],
        "name": "Adam Simpkins"
    },
    {
        "imports": [
            "Jonathan Ellis"
        ],
        "name": "Stu Hood"
    },
    {
        "imports": [
            "Nathan Marz",
            "Tomer Filiba",
            "Jonathan Ellis",
            "Nathan Marz",
            "Nicholas Telford",
            "Nicholas Telford",
            "Nathan Marz",
            "Nathan Marz",
            "Jeff Brown",
            "Nicholas Telford",
            "Bryan Duxbury",
            "Nicholas Telford",
            "Ben Taitelbaum",
            "Adam Simpkins",
            "Dave Lerman",
            "Hua Su"
        ],
        "name": "David Reiss"
    },
    {
        "imports": [
            "Dave Lerman",
            "Dave Lerman",
            "Jeff Brown"
        ],
        "name": "Aron Sogor"
    },
    {
        "imports": [],
        "name": "Dave Lerman"
    },
    {
        "imports": [],
        "name": "James Laver"
    },
    {
        "imports": [],
        "name": "Aran Donohue"
    },
    {
        "imports": [],
        "name": "Johan Stuyts"
    },
    {
        "imports": [
            "Mark Slee",
            "Aron Sogor",
            "Mathias Herberts",
            "David Reiss",
            "Mark Slee"
        ],
        "name": "Jeff Brown"
    },
    {
        "imports": [
            "Bryan Duxbury"
        ],
        "name": "Tomer Filiba"
    },
    {
        "imports": [
            "Aran Donohue",
            "Aran Donohue",
            "Bryan Duxbury"
        ],
        "name": "Mayan"
    },
    {
        "imports": [
            "Nicholas Telford",
            "Bryan Duxbury",
            "James Laver"
        ],
        "name": "Todd Lipcon"
    },
    {
        "imports": [],
        "name": "Gary Rudolph"
    },
    {
        "imports": [],
        "name": "Tony Kamenick"
    },
    {
        "imports": [
            "Bryan Duxbury",
            "David Reiss",
            "Jeff Brown",
            "Jeff Brown"
        ],
        "name": "Mark Slee"
    },
    {
        "imports": [],
        "name": "Nicholas Telford"
    },
    {
        "imports": [
            "Bryan Duxbury",
            "Bryan Duxbury",
            "Bryan Duxbury"
        ],
        "name": "Kevin Clark"
    },
    {
        "imports": [
            "Nicholas Telford"
        ],
        "name": "James Bathgate"
    },
    {
        "imports": [
            "Bryan Duxbury"
        ],
        "name": "Michael Stockton"
    },
    {
        "imports": [
            "Bryan Duxbury"
        ],
        "name": "Larry Kang"
    },
    {
        "imports": [
            "Bryan Duxbury"
        ],
        "name": "Peter Ross"
    },
    {
        "imports": [
            "Johan Stuyts"
        ],
        "name": "Ruslan.usifov"
    },
    {
        "imports": [
            "Kevin Ballard",
            "Kevin Ballard"
        ],
        "name": "Andrew Mcgeachie"
    },
    {
        "imports": [],
        "name": "Kevin Ballard"
    },
    {
        "imports": [
            "Gary Rudolph",
            "Gary Rudolph"
        ],
        "name": "Kay Kay"
    },
    {
        "imports": [],
        "name": "Hua Su"
    },
    {
        "imports": [
            "David Reiss",
            "Tomer Filiba",
            "Peter Ross",
            "Dmitry Chechik",
            "Dmitry Chechik",
            "Eric Jensen",
            "Nathan Marz",
            "Eric Jensen",
            "Larry Kang",
            "Nathan Marz",
            "Larry Kang",
            "Larry Kang",
            "Nathan Marz",
            "Nathan Marz",
            "Tony Kamenick",
            "Dmitry Chechik",
            "David Reiss",
            "Mayan",
            "David Reiss",
            "David Reiss"
        ],
        "name": "Bryan Duxbury"
    },
    {
        "imports": [
            "David Reiss"
        ],
        "name": "Jason Von Nieda"
    },
    {
        "imports": [
            "Gary Rudolph"
        ],
        "name": "Ted Dunning"
    },
    {
        "imports": [],
        "name": "Dmitry Chechik"
    },
    {
        "imports": [],
        "name": "Ben Taitelbaum"
    }
]