[{"imports": [], "name": "Froth"}, {"imports": ["Fguillaume*"], "name": "Shuber"}, {"imports": ["Gcolumbro", "Pmottadelli", "Choeflake"], "name": "Sfermigier*"}, {"imports": [], "name": "Choeflake"}, {"imports": ["Fguillaume*"], "name": "Grabellino"}, {"imports": [], "name": "Sf"}, {"imports": [], "name": "Jira8741"}, {"imports": [], "name": "Mmertins"}, {"imports": ["Marvin", "Fguillaume*"], "name": "Fmeschberger"}, {"imports": [], "name": "Nquinn"}, {"imports": ["Sjohnson"], "name": "Jhuebel"}, {"imports": ["Fguillaume*", "Fguillaume*", "Fguillaume*", "Fguillaume*", "Fguillaume*", "Fguillaume*", "Fguillaume*", "Fguillaume*", "Fguillaume*", "Sf", "Fguillaume*", "Sfermigier*"], "name": "Flo"}, {"imports": ["Fguillaume*"], "name": "Pmottadelli"}, {"imports": [], "name": "Marvin"}, {"imports": ["Flo", "Jira8741", "Flo", "Flo", "Jira8741", "Nquinn", "Nquinn", "Flo", "Froth", "Flo", "Flo", "Flo", "Flo", "Flo", "Fmeschberger", "Flo", "Jira8750", "Jira8750", "Flo", "Gcolumbro", "Gcolumbro", "Jira8750", "Mmertins", "Sjohnson", "Sjohnson", "Michael.duerig"], "name": "Fguillaume*"}, {"imports": ["Fguillaume*", "Jhuebel", "Dnuescheler"], "name": "Sjohnson"}, {"imports": ["Flo", "Sfermigier*", "Fguillaume*"], "name": "Gcolumbro"}, {"imports": ["Nquinn", "Fguillaume*", "Gcolumbro", "Gcolumbro"], "name": "Dcaruana"}, {"imports": ["Fguillaume*", "Sjohnson"], "name": "Dnuescheler"}, {"imports": ["Fguillaume*"], "name": "Michael.duerig"}, {"imports": ["Sjohnson"], "name": "Saperion"}, {"imports": [], "name": "Jira8750"}]