{
    "commit_per_dev": 40.5,
    "end_time": "Feb 13 2013",
    "start_time": "Mar 14 2011",
    "num_emails": 335,
    "status": "Graduated",
    "project_name": "HCatalog",
    "link": "http://incubator.apache.org/projects/hcatalog.html",
    "email_per_dev": 5.58,
    "intro": "HCatalog is a table and storage management service for data created using Apache Hadoop. HCatalog became part of the Hive project",
    "num_senders": 60,
    "num_commits": 162,
    "sponsor": "Incubator",
    "num_committers": 4,
    "to": "Feb 07 2012",
    "from": "Jan 08 2012",
    "num_files": 70
}