{
    "commit_per_dev": 0,
    "end_time": "Sep 19 2012",
    "start_time": "Feb 21 2010",
    "num_emails": 0,
    "status": "Graduated",
    "project_name": "SIS",
    "link": "http://incubator.apache.org/projects/sis.html",
    "email_per_dev": 0,
    "intro": "The Spatial Information System (SIS) Project is a toolkit that spatial information system builders or users can leverage to build applications containing location context.",
    "num_senders": 0,
    "num_commits": 0,
    "sponsor": "Incubator",
    "num_committers": 0,
    "to": "Oct 14 2011",
    "from": "Sep 14 2011",
    "num_files": 0
}