{
   "nodes": [
      {
         "id": "17888",
         "group": 1
      },
      {
         "id": "17870",
         "group": 3
      },
      {
         "id": "17887",
         "group": 3
      },
      {
         "id": "17876",
         "group": 3
      },
      {
         "id": "370",
         "group": 2
      },
      {
         "id": "5137",
         "group": 1
      },
      {
         "id": "1112",
         "group": 3
      },
      {
         "id": "4560",
         "group": 2
      },
      {
         "id": "13240",
         "group": 4
      },
      {
         "id": "17880",
         "group": 2
      },
      {
         "id": "11712",
         "group": 3
      },
      {
         "id": "5081",
         "group": 2
      },
      {
         "id": "17877",
         "group": 3
      },
      {
         "id": "4486",
         "group": 3
      },
      {
         "id": "17889",
         "group": 2
      },
      {
         "id": "319",
         "group": 2
      },
      {
         "id": "13764",
         "group": 1
      },
      {
         "id": "17884",
         "group": 3
      }
   ],
   "links": [
      {
         "value": 1,
         "target": "5137",
         "source": "5081"
      },
      {
         "value": 1,
         "target": "4486",
         "source": "5137"
      },
      {
         "value": 1,
         "target": "319",
         "source": "5137"
      },
      {
         "value": 2,
         "target": "17877",
         "source": "1112"
      },
      {
         "value": 1,
         "target": "17887",
         "source": "4486"
      },
      {
         "value": 2,
         "target": "370",
         "source": "17880"
      },
      {
         "value": 4,
         "target": "11712",
         "source": "1112"
      },
      {
         "value": 6,
         "target": "370",
         "source": "5137"
      },
      {
         "value": 1,
         "target": "370",
         "source": "17888"
      },
      {
         "value": 2,
         "target": "370",
         "source": "4486"
      },
      {
         "value": 1,
         "target": "17877",
         "source": "4560"
      },
      {
         "value": 1,
         "target": "17887",
         "source": "17880"
      },
      {
         "value": 1,
         "target": "17876",
         "source": "1112"
      },
      {
         "value": 3,
         "target": "17889",
         "source": "1112"
      },
      {
         "value": 1,
         "target": "17877",
         "source": "17876"
      },
      {
         "value": 15,
         "target": "17870",
         "source": "1112"
      },
      {
         "value": 1,
         "target": "5137",
         "source": "4486"
      },
      {
         "value": 4,
         "target": "4560",
         "source": "1112"
      },
      {
         "value": 1,
         "target": "4486",
         "source": "319"
      },
      {
         "value": 1,
         "target": "4486",
         "source": "17887"
      },
      {
         "value": 3,
         "target": "370",
         "source": "13764"
      },
      {
         "value": 1,
         "target": "17880",
         "source": "370"
      },
      {
         "value": 2,
         "target": "17884",
         "source": "1112"
      },
      {
         "value": 2,
         "target": "13764",
         "source": "370"
      },
      {
         "value": 3,
         "target": "4486",
         "source": "370"
      },
      {
         "value": 1,
         "target": "370",
         "source": "5081"
      },
      {
         "value": 3,
         "target": "5137",
         "source": "370"
      },
      {
         "value": 1,
         "target": "13240",
         "source": "1112"
      }
   ]
}