{
   "nodes": [
      {
         "id": "11696",
         "group": 3
      },
      {
         "id": "4483",
         "group": 1
      },
      {
         "id": "4099",
         "group": 4
      },
      {
         "id": "28904",
         "group": 3
      },
      {
         "id": "28905",
         "group": 4
      }
   ],
   "links": [
      {
         "value": 19,
         "target": "4099",
         "source": "11696"
      },
      {
         "value": 24,
         "target": "4483",
         "source": "11696"
      },
      {
         "value": 2,
         "target": "28905",
         "source": "4483"
      },
      {
         "value": 18,
         "target": "28904",
         "source": "4483"
      },
      {
         "value": 19,
         "target": "4483",
         "source": "4099"
      },
      {
         "value": 6,
         "target": "28905",
         "source": "11696"
      },
      {
         "value": 18,
         "target": "28904",
         "source": "4099"
      },
      {
         "value": 11,
         "target": "4483",
         "source": "28904"
      },
      {
         "value": 19,
         "target": "28904",
         "source": "11696"
      }
   ]
}