{
   "nodes": [
      {
         "id": "33601",
         "group": 3
      },
      {
         "id": "33604",
         "group": 4
      },
      {
         "id": "33608",
         "group": 2
      },
      {
         "id": "33603",
         "group": 3
      },
      {
         "id": "33618",
         "group": 2
      },
      {
         "id": "11853",
         "group": 2
      },
      {
         "id": "33605",
         "group": 1
      },
      {
         "id": "33607",
         "group": 1
      }
   ],
   "links": [
      {
         "value": 8,
         "target": "33608",
         "source": "33601"
      },
      {
         "value": 63,
         "target": "33607",
         "source": "33603"
      },
      {
         "value": 7,
         "target": "11853",
         "source": "33607"
      },
      {
         "value": 2,
         "target": "33604",
         "source": "33601"
      },
      {
         "value": 21,
         "target": "11853",
         "source": "33601"
      },
      {
         "value": 14,
         "target": "11853",
         "source": "33603"
      },
      {
         "value": 4,
         "target": "11853",
         "source": "33604"
      },
      {
         "value": 70,
         "target": "33607",
         "source": "33601"
      },
      {
         "value": 500,
         "target": "33603",
         "source": "33601"
      },
      {
         "value": 67,
         "target": "33605",
         "source": "33601"
      },
      {
         "value": 8,
         "target": "33608",
         "source": "33603"
      },
      {
         "value": 4,
         "target": "33601",
         "source": "33604"
      },
      {
         "value": 2,
         "target": "33603",
         "source": "33604"
      },
      {
         "value": 2,
         "target": "33603",
         "source": "33605"
      },
      {
         "value": 2,
         "target": "33608",
         "source": "33607"
      },
      {
         "value": 7,
         "target": "33618",
         "source": "33605"
      },
      {
         "value": 6,
         "target": "33607",
         "source": "33604"
      }
   ]
}