{
   "links": [
      {
         "source": "Brent Lintner",
         "value": 1,
         "target": "Raymond Camden"
      },
      {
         "source": "JR",
         "value": 1,
         "target": "Gord Tanner"
      },
      {
         "source": "Brent Lintner",
         "value": 1,
         "target": "Dan Silivestru"
      },
      {
         "source": "Dan Silivestru",
         "value": 1,
         "target": "JR"
      },
      {
         "source": "Gord Tanner",
         "value": 1,
         "target": "Brent Lintner"
      }
   ],
   "nodes": [
      {
         "id": "Gord Tanner",
         "group": 3
      },
      {
         "id": "JR",
         "group": 2
      },
      {
         "id": "Brent Lintner",
         "group": 1
      },
      {
         "id": "Dan Silivestru",
         "group": 4
      },
      {
         "id": "Raymond Camden",
         "group": 2
      }
   ]
}