{
   "links": [
      {
         "target": " 14062",
         "value": 1,
         "source": "14076"
      },
      {
         "target": " 14090",
         "value": 1,
         "source": "13944"
      },
      {
         "target": " 14076",
         "value": 2,
         "source": "13946"
      },
      {
         "target": " 13949",
         "value": 2,
         "source": "4478"
      },
      {
         "target": " 13934",
         "value": 1,
         "source": "13988"
      },
      {
         "target": " 13934",
         "value": 1,
         "source": "14010"
      },
      {
         "target": " 14111",
         "value": 2,
         "source": "13934"
      },
      {
         "target": " 4478",
         "value": 1,
         "source": "13949"
      },
      {
         "target": " 13949",
         "value": 1,
         "source": "13988"
      },
      {
         "target": " 13963",
         "value": 6,
         "source": "13934"
      },
      {
         "target": " 14113",
         "value": 1,
         "source": "14076"
      },
      {
         "target": " 14029",
         "value": 1,
         "source": "13945"
      },
      {
         "target": " 14026",
         "value": 1,
         "source": "14111"
      },
      {
         "target": " 14112",
         "value": 3,
         "source": "13934"
      },
      {
         "target": " 14056",
         "value": 1,
         "source": "378"
      },
      {
         "target": " 13934",
         "value": 2,
         "source": "13936"
      },
      {
         "target": " 13936",
         "value": 1,
         "source": "14105"
      },
      {
         "target": " 13977",
         "value": 1,
         "source": "13944"
      },
      {
         "target": " 13963",
         "value": 1,
         "source": "13944"
      },
      {
         "target": " 14076",
         "value": 1,
         "source": "13989"
      },
      {
         "target": " 13936",
         "value": 2,
         "source": "13937"
      },
      {
         "target": " 13939",
         "value": 1,
         "source": "13934"
      },
      {
         "target": " 14056",
         "value": 1,
         "source": "13937"
      },
      {
         "target": " 13949",
         "value": 5,
         "source": "13934"
      },
      {
         "target": " 13934",
         "value": 1,
         "source": "14026"
      },
      {
         "target": " 13937",
         "value": 1,
         "source": "13936"
      },
      {
         "target": " 14086",
         "value": 1,
         "source": "14074"
      },
      {
         "target": " 13944",
         "value": 1,
         "source": "14090"
      },
      {
         "target": " 13940",
         "value": 1,
         "source": "13937"
      },
      {
         "target": " 4479",
         "value": 1,
         "source": "13934"
      },
      {
         "target": " 13937",
         "value": 3,
         "source": "13947"
      },
      {
         "target": " 13934",
         "value": 6,
         "source": "13977"
      },
      {
         "target": " 13947",
         "value": 1,
         "source": "13936"
      },
      {
         "target": " 13944",
         "value": 1,
         "source": "14010"
      },
      {
         "target": " 13937",
         "value": 1,
         "source": "378"
      },
      {
         "target": " 14056",
         "value": 1,
         "source": "13939"
      },
      {
         "target": " 378",
         "value": 2,
         "source": "13937"
      },
      {
         "target": " 14077",
         "value": 1,
         "source": "13939"
      },
      {
         "target": " 14083",
         "value": 2,
         "source": "13934"
      },
      {
         "target": " 4478",
         "value": 3,
         "source": "13934"
      },
      {
         "target": " 13936",
         "value": 1,
         "source": "13996"
      },
      {
         "target": " 14010",
         "value": 1,
         "source": "13934"
      },
      {
         "target": " 14105",
         "value": 1,
         "source": "13934"
      },
      {
         "target": " 13937",
         "value": 1,
         "source": "14053"
      },
      {
         "target": " 13934",
         "value": 3,
         "source": "13949"
      },
      {
         "target": " 13934",
         "value": 1,
         "source": "14090"
      },
      {
         "target": " 13937",
         "value": 1,
         "source": "14049"
      },
      {
         "target": " 13934",
         "value": 1,
         "source": "14086"
      },
      {
         "target": " 13934",
         "value": 3,
         "source": "14112"
      },
      {
         "target": " 13937",
         "value": 1,
         "source": "13939"
      },
      {
         "target": " 13963",
         "value": 2,
         "source": "14076"
      },
      {
         "target": " 13939",
         "value": 1,
         "source": "13945"
      },
      {
         "target": " 13936",
         "value": 1,
         "source": "13963"
      },
      {
         "target": " 13934",
         "value": 5,
         "source": "13947"
      },
      {
         "target": " 13934",
         "value": 1,
         "source": "4479"
      },
      {
         "target": " 14010",
         "value": 2,
         "source": "13937"
      },
      {
         "target": " 13947",
         "value": 1,
         "source": "13937"
      },
      {
         "target": " 13947",
         "value": 1,
         "source": "13963"
      },
      {
         "target": " 13934",
         "value": 1,
         "source": "14103"
      },
      {
         "target": " 13934",
         "value": 2,
         "source": "13944"
      },
      {
         "target": " 13934",
         "value": 6,
         "source": "3873"
      },
      {
         "target": " 14062",
         "value": 1,
         "source": "13957"
      },
      {
         "target": " 13934",
         "value": 2,
         "source": "14050"
      },
      {
         "target": " 13977",
         "value": 2,
         "source": "13934"
      },
      {
         "target": " 13934",
         "value": 26,
         "source": "13937"
      },
      {
         "target": " 14050",
         "value": 1,
         "source": "13945"
      },
      {
         "target": " 14112",
         "value": 1,
         "source": "3873"
      },
      {
         "target": " 13940",
         "value": 3,
         "source": "13934"
      },
      {
         "target": " 14103",
         "value": 1,
         "source": "13989"
      },
      {
         "target": " 14090",
         "value": 1,
         "source": "13937"
      },
      {
         "target": " 13963",
         "value": 4,
         "source": "13937"
      },
      {
         "target": " 13934",
         "value": 1,
         "source": "14015"
      },
      {
         "target": " 14015",
         "value": 1,
         "source": "13937"
      },
      {
         "target": " 13934",
         "value": 1,
         "source": "13945"
      },
      {
         "target": " 13934",
         "value": 1,
         "source": "4478"
      },
      {
         "target": " 14053",
         "value": 2,
         "source": "13937"
      },
      {
         "target": " 14103",
         "value": 2,
         "source": "13937"
      },
      {
         "target": " 14083",
         "value": 1,
         "source": "13936"
      },
      {
         "target": " 13963",
         "value": 2,
         "source": "13949"
      },
      {
         "target": " 14056",
         "value": 3,
         "source": "13934"
      },
      {
         "target": " 3873",
         "value": 1,
         "source": "13937"
      },
      {
         "target": " 13936",
         "value": 1,
         "source": "13940"
      },
      {
         "target": " 14088",
         "value": 1,
         "source": "13947"
      },
      {
         "target": " 13940",
         "value": 1,
         "source": "14049"
      },
      {
         "target": " 14063",
         "value": 1,
         "source": "13937"
      },
      {
         "target": " 5966",
         "value": 1,
         "source": "13934"
      },
      {
         "target": " 13937",
         "value": 3,
         "source": "13949"
      },
      {
         "target": " 14083",
         "value": 1,
         "source": "14076"
      },
      {
         "target": " 46134",
         "value": 1,
         "source": "14076"
      },
      {
         "target": " 13934",
         "value": 2,
         "source": "14076"
      },
      {
         "target": " 13934",
         "value": 1,
         "source": "14064"
      },
      {
         "target": " 14116",
         "value": 1,
         "source": "13937"
      },
      {
         "target": " 13934",
         "value": 3,
         "source": "13940"
      },
      {
         "target": " 14088",
         "value": 1,
         "source": "13937"
      },
      {
         "target": " 13965",
         "value": 1,
         "source": "13934"
      },
      {
         "target": " 14103",
         "value": 1,
         "source": "13977"
      },
      {
         "target": " 13945",
         "value": 2,
         "source": "13949"
      },
      {
         "target": " 13937",
         "value": 1,
         "source": "14077"
      },
      {
         "target": " 13944",
         "value": 1,
         "source": "46134"
      },
      {
         "target": " 13934",
         "value": 9,
         "source": "13963"
      },
      {
         "target": " 13939",
         "value": 2,
         "source": "14056"
      },
      {
         "target": " 13947",
         "value": 2,
         "source": "13934"
      },
      {
         "target": " 13937",
         "value": 9,
         "source": "13934"
      },
      {
         "target": " 13963",
         "value": 1,
         "source": "13936"
      },
      {
         "target": " 3873",
         "value": 2,
         "source": "13949"
      },
      {
         "target": " 14076",
         "value": 1,
         "source": "13934"
      },
      {
         "target": " 13949",
         "value": 3,
         "source": "3873"
      },
      {
         "target": " 14114",
         "value": 1,
         "source": "13937"
      },
      {
         "target": " 13988",
         "value": 1,
         "source": "14026"
      },
      {
         "target": " 393",
         "value": 1,
         "source": "13934"
      },
      {
         "target": " 13944",
         "value": 1,
         "source": "14064"
      },
      {
         "target": " 13989",
         "value": 1,
         "source": "13937"
      },
      {
         "target": " 13977",
         "value": 1,
         "source": "14029"
      },
      {
         "target": " 14105",
         "value": 1,
         "source": "13936"
      },
      {
         "target": " 13934",
         "value": 1,
         "source": "34880"
      },
      {
         "target": " 13989",
         "value": 1,
         "source": "13963"
      },
      {
         "target": " 13977",
         "value": 2,
         "source": "3873"
      },
      {
         "target": " 14103",
         "value": 1,
         "source": "13934"
      },
      {
         "target": " 14062",
         "value": 1,
         "source": "14064"
      },
      {
         "target": " 3873",
         "value": 7,
         "source": "13934"
      },
      {
         "target": " 14091",
         "value": 1,
         "source": "14114"
      },
      {
         "target": " 14077",
         "value": 1,
         "source": "13947"
      },
      {
         "target": " 13934",
         "value": 3,
         "source": "13989"
      },
      {
         "target": " 13936",
         "value": 1,
         "source": "14010"
      },
      {
         "target": " 14076",
         "value": 1,
         "source": "14074"
      },
      {
         "target": " 13934",
         "value": 1,
         "source": "14028"
      },
      {
         "target": " 13934",
         "value": 2,
         "source": "14062"
      },
      {
         "target": " 13937",
         "value": 5,
         "source": "13963"
      },
      {
         "target": " 13949",
         "value": 3,
         "source": "13937"
      },
      {
         "target": " 13949",
         "value": 2,
         "source": "13963"
      },
      {
         "target": " 13937",
         "value": 1,
         "source": "14064"
      },
      {
         "target": " 13977",
         "value": 1,
         "source": "13936"
      },
      {
         "target": " 13936",
         "value": 1,
         "source": "13934"
      },
      {
         "target": " 13934",
         "value": 3,
         "source": "13939"
      },
      {
         "target": " 13949",
         "value": 2,
         "source": "13977"
      },
      {
         "target": " 14114",
         "value": 1,
         "source": "13934"
      }
   ],
   "nodes": [
      {
         "group": 3,
         "id": "13963"
      },
      {
         "group": 3,
         "id": "13934"
      },
      {
         "group": 2,
         "id": "14074"
      },
      {
         "group": 4,
         "id": "13989"
      },
      {
         "group": 2,
         "id": "14063"
      },
      {
         "group": 1,
         "id": "393"
      },
      {
         "group": 4,
         "id": "14062"
      },
      {
         "group": 2,
         "id": "14028"
      },
      {
         "group": 3,
         "id": "13977"
      },
      {
         "group": 4,
         "id": "14103"
      },
      {
         "group": 1,
         "id": "14088"
      },
      {
         "group": 1,
         "id": "14064"
      },
      {
         "group": 4,
         "id": "13947"
      },
      {
         "group": 1,
         "id": "14113"
      },
      {
         "group": 1,
         "id": "13944"
      },
      {
         "group": 1,
         "id": "14050"
      },
      {
         "group": 1,
         "id": "14015"
      },
      {
         "group": 2,
         "id": "3873"
      },
      {
         "group": 3,
         "id": "378"
      },
      {
         "group": 4,
         "id": "13949"
      },
      {
         "group": 4,
         "id": "14091"
      },
      {
         "group": 1,
         "id": "13945"
      },
      {
         "group": 2,
         "id": "13988"
      },
      {
         "group": 2,
         "id": "14112"
      },
      {
         "group": 2,
         "id": "14111"
      },
      {
         "group": 2,
         "id": "14083"
      },
      {
         "group": 4,
         "id": "13965"
      },
      {
         "group": 4,
         "id": "14114"
      },
      {
         "group": 4,
         "id": "13936"
      },
      {
         "group": 4,
         "id": "14026"
      },
      {
         "group": 4,
         "id": "14053"
      },
      {
         "group": 2,
         "id": "14010"
      },
      {
         "group": 2,
         "id": "34880"
      },
      {
         "group": 4,
         "id": "13946"
      },
      {
         "group": 4,
         "id": "13957"
      },
      {
         "group": 1,
         "id": "14056"
      },
      {
         "group": 4,
         "id": "14090"
      },
      {
         "group": 4,
         "id": "46134"
      },
      {
         "group": 1,
         "id": "14077"
      },
      {
         "group": 1,
         "id": "13939"
      },
      {
         "group": 3,
         "id": "4478"
      },
      {
         "group": 2,
         "id": "13937"
      },
      {
         "group": 2,
         "id": "14076"
      },
      {
         "group": 4,
         "id": "14116"
      },
      {
         "group": 3,
         "id": "14105"
      },
      {
         "group": 2,
         "id": "14049"
      },
      {
         "group": 3,
         "id": "14029"
      },
      {
         "group": 1,
         "id": "13940"
      },
      {
         "group": 2,
         "id": "14086"
      },
      {
         "group": 2,
         "id": "13996"
      },
      {
         "group": 2,
         "id": "5966"
      },
      {
         "group": 3,
         "id": "4479"
      }
   ]
}